<?xml version="1.0"?>
<GHShowerSimulation> 
<Shower type="GHShower"> 
<Emin> 0.49807 </Emin>
<Emax>0.49807</Emax>
<alpha> -3 </alpha>
<minZen> 20.8467 </minZen>
<maxZen> 20.8467 </maxZen>
<minAzi> 122.982 </minAzi>
<maxAzi> 122.982 </maxAzi>
<coreRandomization type="fixed">
<x> -13224.2 </x>
<y> -23891.8 </y>
<z> 0 </z>
</coreRandomization>
<primary> 100 </primary>
<fluctuatePrimaryProperties> 0 </fluctuatePrimaryProperties>
 <fluctuateShowerParameterization> 1 </fluctuateShowerParameterization>
</Shower>
</GHShowerSimulation>